ms_teams_sdk/__init__.py
ms_teams_sdk/auth.py
ms_teams_sdk/exception.py
ms_teams_sdk/lists.py
ms_teams_sdk/message.py
ms_teams_sdk/users.py
ms_teams_sdk-0.0.1.dist-info/LICENSE
ms_teams_sdk-0.0.1.dist-info/METADATA
ms_teams_sdk-0.0.1.dist-info/WHEEL
ms_teams_sdk-0.0.1.dist-info/top_level.txt
ms_teams_sdk-0.0.1.dist-info/RECORD
